SloppyV4/api.py
SloppyV4/common.py
SloppyV4/config.py
SloppyV4/database.py
SloppyV4/error.py
SloppyV4/excel.py
SloppyV4/json.py
SloppyV4/log.py
SloppyV4/message.py
SloppyV4/remote.py
SloppyV4/security.py
SloppyV4-0.0.0.0.0.0.0.1.dist-info/METADATA
SloppyV4-0.0.0.0.0.0.0.1.dist-info/WHEEL
SloppyV4-0.0.0.0.0.0.0.1.dist-info/top_level.txt
SloppyV4-0.0.0.0.0.0.0.1.dist-info/RECORD
