Metadata-Version: 2.1
Name: SloppyV4
Version: 0.0.0.0.0.0.0.1
Summary: Python module - SloppyV4
Home-page: https://github.com/Cheung-man/SloppyV4.git
Author: Chungman Kim
Author-email: h2noda@gmail.com
Requires-Python: >=3.12
Requires-Dist: beautifulsoup4
Requires-Dist: openpyxl
Requires-Dist: rich
Requires-Dist: python-dateutil
Requires-Dist: paramiko
Requires-Dist: cryptography
